moleculetda/__init__.py
moleculetda/cli.py
moleculetda/construct_pd.py
moleculetda/io.py
moleculetda/metrics.py
moleculetda/plotting.py
moleculetda/read_file.py
moleculetda/structure_to_vectorization.py
moleculetda/vectorize_pds.py
moleculetda/version.py
moleculetda-0.2.1.dist-info/LICENSE
moleculetda-0.2.1.dist-info/METADATA
moleculetda-0.2.1.dist-info/WHEEL
moleculetda-0.2.1.dist-info/entry_points.txt
moleculetda-0.2.1.dist-info/top_level.txt
moleculetda-0.2.1.dist-info/RECORD
