Metadata-Version: 2.1
Name: moleculetda
Version: 0.2.1
Summary: Toolkit for using topological data analysis representations.
Home-page: https://github.com/a1k12/molecule-tda
Author: Aditi Krishnapriyan
Author-email: akrishnapriyan@lbl.gov
Maintainer-email: akrishnapriyan@lbl.gov
License: MIT
Download-URL: https://github.com/a1k12/molecule-tdal/releases
Project-URL: Bug Tracker, https://github.com/a1k12/molecule-tda/issues
Project-URL: Source Code, https://github.com/a1k12/molecule-tda/
Platform: UNKNOWN
Classifier: Development Status :: 1 - Planning
Classifier: Environment :: Console
Classifier: Intended Audience :: Developers
Classifier: License :: OSI Approved :: MIT License
Classifier: Operating System :: OS Independent
Classifier: Framework :: Pytest
Classifier: Framework :: tox
Classifier: Framework :: Sphinx
Classifier: Programming Language :: Python
Classifier: Programming Language :: Python :: 3.8
Classifier: Programming Language :: Python :: 3.9
Classifier: Programming Language :: Python :: 3.10
Classifier: Programming Language :: Python :: 3 :: Only
Requires-Python: >=3.8
License-File: LICENSE
Requires-Dist: scikit-learn
Requires-Dist: dionysus
Requires-Dist: numpy
Requires-Dist: pyclustering
Requires-Dist: pymatgen
Requires-Dist: diode
Requires-Dist: loguru
Requires-Dist: click
Provides-Extra: docs
Requires-Dist: sphinx ; extra == 'docs'
Requires-Dist: furo ; extra == 'docs'
Requires-Dist: sphinx-click ; extra == 'docs'
Requires-Dist: sphinx-autodoc-typehints ; extra == 'docs'
Requires-Dist: sphinx-automodapi ; extra == 'docs'
Requires-Dist: sphinx-copybutton ; extra == 'docs'
Requires-Dist: sphinxcontrib-katex ; extra == 'docs'
